anon_traffic/__init__.py
anon_traffic/disanon.py
anon_traffic/utils.py
anon_traffic/myutils/__init__.py
anon_traffic/myutils/config.py
anon_traffic/myutils/logger.py
anon_traffic-1.0.4.dist-info/METADATA
anon_traffic-1.0.4.dist-info/WHEEL
anon_traffic-1.0.4.dist-info/entry_points.txt
anon_traffic-1.0.4.dist-info/top_level.txt
anon_traffic-1.0.4.dist-info/RECORD
