Metadata-Version: 2.1
Name: anon_traffic
Version: 1.0.4
Summary: disanon ip and port
Home-page: https://github.com/aimafan/anon_traffic
Author: aimafan
Author-email: chongrufan@nuaa.edu.cn
Classifier: Programming Language :: Python :: 3
Classifier: License :: OSI Approved :: MIT License
Classifier: Operating System :: OS Independent
Requires-Python: >=3.6
Requires-Dist: cryptography
